Metadata-Version: 2.1
Name: stitch-sdk
Version: 0.0.2
Summary: Unofficial Stitch Python SDK
Home-page: https://github.com/deanpienaar/stitch-py
Author: Dean Pienaar
License: MIT
License-File: LICENSE
